pz_rail_gpz_v1-1.1.5.dist-info/licenses/LICENSE
rail/estimation/algos/_gpz_util.py
rail/estimation/algos/gpz.py
rail/gpz/__init__.py
rail/gpz/_version.py
pz_rail_gpz_v1-1.1.5.dist-info/METADATA
pz_rail_gpz_v1-1.1.5.dist-info/WHEEL
pz_rail_gpz_v1-1.1.5.dist-info/top_level.txt
pz_rail_gpz_v1-1.1.5.dist-info/RECORD
